pyillion/__init__.py
pyillion/illionifyer.py
pyillion-1.2.0.dist-info/licenses/LICENSE
pyillion-1.2.0.dist-info/METADATA
pyillion-1.2.0.dist-info/WHEEL
pyillion-1.2.0.dist-info/top_level.txt
pyillion-1.2.0.dist-info/RECORD
