Metadata-Version: 2.4
Name: pyillion
Version: 1.2.0
Summary: Convert integers into long-form -illion notation (million, billion, ...)
Author-email: Phannoiershit <buiphan022109@gmail.com>
License: MIT
Project-URL: Homepage, https://github.com/phannoiershit/pyillion
Project-URL: Source, https://github.com/phannoiershit/pyillion
Project-URL: Issues, https://github.com/phannoiershit/pyillion/issues
Keywords: illion,big-number,number-format,math
Classifier: Programming Language :: Python :: 3
Classifier: Programming Language :: Python :: 3 :: Only
Classifier: License :: OSI Approved :: MIT License
Classifier: Operating System :: OS Independent
Classifier: Topic :: Scientific/Engineering :: Mathematics
Classifier: Topic :: Software Development :: Libraries
Requires-Python: >=3.8
License-File: LICENSE
Dynamic: license-file
